subprocessmagic/__init__.py
subprocessmagic/_mod.py
subprocessmagic/py.typed
subprocessmagic-2.0.0.dist-info/LICENSE
subprocessmagic-2.0.0.dist-info/METADATA
subprocessmagic-2.0.0.dist-info/WHEEL
subprocessmagic-2.0.0.dist-info/RECORD
